Metadata-Version: 2.1
Name: s-area
Version: 0.0
Summary: Calculating the area of a circle, triangle, and parallelepiped
Home-page: UNKNOWN
Author-email: 1132232888@pfur.ru
License: UNKNOWN
Platform: UNKNOWN
